MANIFEST.in
README.txt
distribute_setup.py
pygora.py
setup.py
pygora.egg-info/PKG-INFO
pygora.egg-info/SOURCES.txt
pygora.egg-info/dependency_links.txt
pygora.egg-info/entry_points.txt
pygora.egg-info/top_level.txt
tests/.coverage
tests/__init__.py
tests/__init__.pyc
tests/test_pygora.py
tests/test_pygora.pyc