Metadata-Version: 1.0
Name: pygora
Version: 0.0.3
Summary: A simple way to get a nice ratio between your test code and your source code
Home-page: http://code.google.com/p/pygora
Author: Alfredo Deza
Author-email: alfredodeza [at] gmail.com
License: MIT
Keywords: test code ratio compare count lines
Platform: UNKNOWN
